README.md
setup.cfg
setup.py
distributions_dboland77/Binomialdistribution.py
distributions_dboland77/Gaussiandistribution.py
distributions_dboland77/Generaldistribution.py
distributions_dboland77/__init__.py
distributions_dboland77.egg-info/PKG-INFO
distributions_dboland77.egg-info/SOURCES.txt
distributions_dboland77.egg-info/dependency_links.txt
distributions_dboland77.egg-info/not-zip-safe
distributions_dboland77.egg-info/top_level.txt